neuroviz-0.4.0.dist-info/METADATA
neuroviz-0.4.0.dist-info/WHEEL
neuroviz/__init__.py
neuroviz/__init__.pyi
neuroviz/py.typed
neuroviz/neuroviz.abi3.so
neuroviz-0.4.0.dist-info/RECORD
